[{"date":"01-03-2020","death":0,"hospitalizations":0},{"date":"01-04-2020","death":0,"hospitalizations":0},{"date":"01-05-2020","death":0,"hospitalizations":0},{"date":"01-06-2020","death":0,"hospitalizations":0},{"date":"01-07-2020","death":0,"hospitalizations":0},{"date":"01-08-2020","death":0,"hospitalizations":0},{"date":"01-09-2020","death":0,"hospitalizations":0},{"date":"01-10-2020","death":0,"hospitalizations":0},{"date":"01-11-2020","death":0,"hospitalizations":0},{"date":"01-12-2020","death":0,"hospitalizations":0},{"date":"01-13-2020","death":0,"hospitalizations":0},{"date":"01-14-2020","death":0,"hospitalizations":0},{"date":"01-15-2020","death":0,"hospitalizations":0},{"date":"01-16-2020","death":0,"hospitalizations":0},{"date":"01-17-2020","death":0,"hospitalizations":0},{"date":"01-18-2020","death":0,"hospitalizations":0},{"date":"01-19-2020","death":0,"hospitalizations":0},{"date":"01-20-2020","death":0,"hospitalizations":0},{"date":"01-21-2020","death":0,"hospitalizations":0},{"date":"01-22-2020","death":0,"hospitalizations":0},{"date":"01-23-2020","death":0,"hospitalizations":0},{"date":"01-24-2020","death":0,"hospitalizations":0},{"date":"01-25-2020","death":0,"hospitalizations":0},{"date":"01-26-2020","death":0,"hospitalizations":0},{"date":"01-27-2020","death":0,"hospitalizations":0},{"date":"01-28-2020","death":0,"hospitalizations":0},{"date":"01-29-2020","death":0,"hospitalizations":0},{"date":"01-30-2020","death":0,"hospitalizations":0},{"date":"01-31-2020","death":0,"hospitalizations":0},{"date":"02-01-2020","death":0,"hospitalizations":0},{"date":"02-02-2020","death":0,"hospitalizations":0},{"date":"02-03-2020","death":0,"hospitalizations":0},{"date":"02-04-2020","death":0,"hospitalizations":0},{"date":"02-05-2020","death":0,"hospitalizations":0},{"date":"02-06-2020","death":0,"hospitalizations":0},{"date":"02-07-2020","death":0,"hospitalizations":0},{"date":"02-08-2020","death":0,"hospitalizations":0},{"date":"02-09-2020","death":0,"hospitalizations":0},{"date":"02-10-2020","death":0,"hospitalizations":0},{"date":"02-11-2020","death":0,"hospitalizations":0},{"date":"02-12-2020","death":0,"hospitalizations":0},{"date":"02-13-2020","death":0,"hospitalizations":0},{"date":"02-14-2020","death":0,"hospitalizations":0},{"date":"02-15-2020","death":0,"hospitalizations":0},{"date":"02-16-2020","death":0,"hospitalizations":0},{"date":"02-17-2020","death":0,"hospitalizations":0},{"date":"02-18-2020","death":0,"hospitalizations":0},{"date":"02-19-2020","death":0,"hospitalizations":0},{"date":"02-20-2020","death":0,"hospitalizations":0},{"date":"02-21-2020","death":0,"hospitalizations":0},{"date":"02-22-2020","death":0,"hospitalizations":0},{"date":"02-23-2020","death":0,"hospitalizations":0},{"date":"02-24-2020","death":0,"hospitalizations":0},{"date":"02-25-2020","death":0,"hospitalizations":0},{"date":"02-26-2020","death":0,"hospitalizations":0},{"date":"02-27-2020","death":0,"hospitalizations":0},{"date":"02-28-2020","death":0,"hospitalizations":0},{"date":"02-29-2020","death":0,"hospitalizations":0},{"date":"03-01-2020","death":0,"hospitalizations":0},{"date":"03-02-2020","death":0,"hospitalizations":0},{"date":"03-03-2020","death":0,"hospitalizations":0},{"date":"03-04-2020","death":0,"hospitalizations":0},{"date":"03-05-2020","death":0,"hospitalizations":0},{"date":"03-06-2020","death":0,"hospitalizations":0},{"date":"03-07-2020","death":0,"hospitalizations":0},{"date":"03-08-2020","death":0,"hospitalizations":0},{"date":"03-09-2020","death":0,"hospitalizations":0},{"date":"03-10-2020","death":0,"hospitalizations":0},{"date":"03-11-2020","death":0,"hospitalizations":0},{"date":"03-12-2020","death":0,"hospitalizations":0},{"date":"03-13-2020","death":0,"hospitalizations":0},{"date":"03-14-2020","death":0,"hospitalizations":0},{"date":"03-15-2020","death":0,"hospitalizations":0},{"date":"03-16-2020","death":0,"hospitalizations":0},{"date":"03-17-2020","death":0,"hospitalizations":0},{"date":"03-18-2020","death":0,"hospitalizations":0},{"date":"03-19-2020","death":0,"hospitalizations":0},{"date":"03-20-2020","death":0,"hospitalizations":0},{"date":"03-21-2020","death":0,"hospitalizations":0},{"date":"03-22-2020","death":0,"hospitalizations":0},{"date":"03-23-2020","death":0,"hospitalizations":13.4987064101061},{"date":"03-24-2020","death":0,"hospitalizations":20.1892275525086},{"date":"03-25-2020","death":0,"hospitalizations":27.0276130865651},{"date":"03-26-2020","death":0,"hospitalizations":54.0186396057632},{"date":"03-27-2020","death":0,"hospitalizations":67.4409691616777},{"date":"03-28-2020","death":2,"hospitalizations":80.9055276015737},{"date":"03-29-2020","death":3,"hospitalizations":92.3872733330438},{"date":"03-30-2020","death":4,"hospitalizations":100.890829175993},{"date":"03-31-2020","death":8,"hospitalizations":148.506778444629},{"date":"04-01-2020","death":10,"hospitalizations":152.535180796719},{"date":"04-02-2020","death":12,"hospitalizations":149.1740539215},{"date":"04-03-2020","death":14,"hospitalizations":203.416969034556},{"date":"04-04-2020","death":17,"hospitalizations":258.918203207229},{"date":"04-05-2020","death":25,"hospitalizations":323.207566005963},{"date":"04-06-2020","death":27,"hospitalizations":387.558282207228},{"date":"04-07-2020","death":30,"hospitalizations":440.109273123986},{"date":"04-08-2020","death":39.947,"hospitalizations":533.225926827288},{"date":"04-09-2020","death":50.062,"hospitalizations":623.757232041239},{"date":"04-10-2020","death":61.691,"hospitalizations":685.513042268907},{"date":"04-11-2020","death":74.756,"hospitalizations":755.620780154757},{"date":"04-12-2020","death":89.204,"hospitalizations":823.656065712358},{"date":"04-13-2020","death":105.077,"hospitalizations":891.081818517937},{"date":"04-14-2020","death":122.353,"hospitalizations":962.083913068227},{"date":"04-15-2020","death":140.904,"hospitalizations":1030.14230286181},{"date":"04-16-2020","death":161.106,"hospitalizations":1101.33754887373},{"date":"04-17-2020","death":182.459,"hospitalizations":1164.26098506618},{"date":"04-18-2020","death":205.152,"hospitalizations":1222.98533386379},{"date":"04-19-2020","death":229.637,"hospitalizations":1279.8486858025},{"date":"04-20-2020","death":255.198,"hospitalizations":1333.94512558019},{"date":"04-21-2020","death":282.388,"hospitalizations":1368.47471810536},{"date":"04-22-2020","death":309.721,"hospitalizations":1409.20249868015},{"date":"04-23-2020","death":337.918,"hospitalizations":1438.90162544169},{"date":"04-24-2020","death":366.929,"hospitalizations":1469.01355503343},{"date":"04-25-2020","death":397.15,"hospitalizations":1471.02403364102},{"date":"04-26-2020","death":425.755,"hospitalizations":1449.89341136816},{"date":"04-27-2020","death":456.227,"hospitalizations":1432.26531358278},{"date":"04-28-2020","death":486.989,"hospitalizations":1399.52277611307},{"date":"04-29-2020","death":517.872,"hospitalizations":1349.22440744016},{"date":"04-30-2020","death":545.426,"hospitalizations":1285.77452267571},{"date":"05-01-2020","death":570.737,"hospitalizations":1223.69018974364},{"date":"05-02-2020","death":597.155,"hospitalizations":1167.4549130694},{"date":"05-03-2020","death":620.407,"hospitalizations":1117.73357136564},{"date":"05-04-2020","death":642.875,"hospitalizations":1053.51900265957},{"date":"05-05-2020","death":663.606,"hospitalizations":994.481265456804},{"date":"05-06-2020","death":684.179,"hospitalizations":935.996369167},{"date":"05-07-2020","death":702.817,"hospitalizations":875.288696636117},{"date":"05-08-2020","death":720.72,"hospitalizations":809.611989848258},{"date":"05-09-2020","death":737.119,"hospitalizations":742.898074220074},{"date":"05-10-2020","death":751.669,"hospitalizations":671.44874779142},{"date":"05-11-2020","death":765.429,"hospitalizations":605.165037954138},{"date":"05-12-2020","death":777.475,"hospitalizations":541.445646473414},{"date":"05-13-2020","death":788.506,"hospitalizations":478.677291419571},{"date":"05-14-2020","death":797.67,"hospitalizations":422.405096707378},{"date":"05-15-2020","death":805.355,"hospitalizations":368.835638712182},{"date":"05-16-2020","death":812.265,"hospitalizations":324.844855590862},{"date":"05-17-2020","death":818.102,"hospitalizations":284.035014461798},{"date":"05-18-2020","death":823.208,"hospitalizations":247.142430770983},{"date":"05-19-2020","death":827.73,"hospitalizations":214.3788873532},{"date":"05-20-2020","death":831.441,"hospitalizations":184.541001140646},{"date":"05-21-2020","death":834.715,"hospitalizations":156.711473951985},{"date":"05-22-2020","death":837.228,"hospitalizations":133.099629716263},{"date":"05-23-2020","death":839.418,"hospitalizations":111.985169504511},{"date":"05-24-2020","death":841.199,"hospitalizations":94.4779783631874},{"date":"05-25-2020","death":842.656,"hospitalizations":79.034488814896},{"date":"05-26-2020","death":843.797,"hospitalizations":65.7762323547196},{"date":"05-27-2020","death":844.746,"hospitalizations":54.5270771594118},{"date":"05-28-2020","death":845.59,"hospitalizations":44.9997835334858},{"date":"05-29-2020","death":846.23,"hospitalizations":36.7511966990354},{"date":"05-30-2020","death":846.725,"hospitalizations":29.3889772228975},{"date":"05-31-2020","death":847.12,"hospitalizations":23.4215183192066},{"date":"06-01-2020","death":847.421,"hospitalizations":18.388965401347},{"date":"06-02-2020","death":847.649,"hospitalizations":14.2448847304828},{"date":"06-03-2020","death":847.801,"hospitalizations":10.817204753395},{"date":"06-04-2020","death":847.882,"hospitalizations":8.09394410276256},{"date":"06-05-2020","death":847.945,"hospitalizations":5.99566786528745},{"date":"06-06-2020","death":847.969,"hospitalizations":4.594642906702},{"date":"06-07-2020","death":847.987,"hospitalizations":3.43845051786449},{"date":"06-08-2020","death":847.995,"hospitalizations":2.63989073173558},{"date":"06-09-2020","death":847.997,"hospitalizations":2.01250400310474},{"date":"06-10-2020","death":847.999,"hospitalizations":1.5462759515811},{"date":"06-11-2020","death":847.999,"hospitalizations":1.18895277002409},{"date":"06-12-2020","death":847.999,"hospitalizations":0.873324257931611},{"date":"06-13-2020","death":847.999,"hospitalizations":0.649002147852148},{"date":"06-14-2020","death":847.999,"hospitalizations":0.462915653137712},{"date":"06-15-2020","death":847.999,"hospitalizations":0.326752935055141},{"date":"06-16-2020","death":847.999,"hospitalizations":0.217010631117249},{"date":"06-17-2020","death":847.999,"hospitalizations":0.132602612501877},{"date":"06-18-2020","death":847.999,"hospitalizations":0.07424088174897},{"date":"06-19-2020","death":847.999,"hospitalizations":0.0466560042082101},{"date":"06-20-2020","death":847.999,"hospitalizations":0.0229111255574491},{"date":"06-21-2020","death":847.999,"hospitalizations":0.0118436059855178},{"date":"06-22-2020","death":847.999,"hospitalizations":0.00570937395937396},{"date":"06-23-2020","death":847.999,"hospitalizations":0.00261904761904762},{"date":"06-24-2020","death":847.999,"hospitalizations":0.000619047619047619},{"date":"06-25-2020","death":847.999,"hospitalizations":0},{"date":"06-26-2020","death":847.999,"hospitalizations":0},{"date":"06-27-2020","death":847.999,"hospitalizations":0},{"date":"06-28-2020","death":847.999,"hospitalizations":0},{"date":"06-29-2020","death":847.999,"hospitalizations":0},{"date":"06-30-2020","death":847.999,"hospitalizations":0},{"date":"07-01-2020","death":847.999,"hospitalizations":0},{"date":"07-02-2020","death":847.999,"hospitalizations":0},{"date":"07-03-2020","death":847.999,"hospitalizations":0},{"date":"07-04-2020","death":847.999,"hospitalizations":0},{"date":"07-05-2020","death":847.999,"hospitalizations":0},{"date":"07-06-2020","death":847.999,"hospitalizations":0},{"date":"07-07-2020","death":847.999,"hospitalizations":0},{"date":"07-08-2020","death":847.999,"hospitalizations":0},{"date":"07-09-2020","death":847.999,"hospitalizations":0},{"date":"07-10-2020","death":847.999,"hospitalizations":0},{"date":"07-11-2020","death":847.999,"hospitalizations":0},{"date":"07-12-2020","death":847.999,"hospitalizations":0},{"date":"07-13-2020","death":847.999,"hospitalizations":0},{"date":"07-14-2020","death":847.999,"hospitalizations":0},{"date":"07-15-2020","death":847.999,"hospitalizations":0},{"date":"07-16-2020","death":847.999,"hospitalizations":0},{"date":"07-17-2020","death":847.999,"hospitalizations":0},{"date":"07-18-2020","death":847.999,"hospitalizations":0},{"date":"07-19-2020","death":847.999,"hospitalizations":0},{"date":"07-20-2020","death":847.999,"hospitalizations":0},{"date":"07-21-2020","death":847.999,"hospitalizations":0},{"date":"07-22-2020","death":847.999,"hospitalizations":0},{"date":"07-23-2020","death":847.999,"hospitalizations":0},{"date":"07-24-2020","death":847.999,"hospitalizations":0},{"date":"07-25-2020","death":847.999,"hospitalizations":0},{"date":"07-26-2020","death":847.999,"hospitalizations":0},{"date":"07-27-2020","death":847.999,"hospitalizations":0},{"date":"07-28-2020","death":847.999,"hospitalizations":0},{"date":"07-29-2020","death":847.999,"hospitalizations":0},{"date":"07-30-2020","death":847.999,"hospitalizations":0},{"date":"07-31-2020","death":847.999,"hospitalizations":0},{"date":"08-01-2020","death":847.999,"hospitalizations":0},{"date":"08-02-2020","death":847.999,"hospitalizations":0},{"date":"08-03-2020","death":847.999,"hospitalizations":0},{"date":"08-04-2020","death":847.999,"hospitalizations":0}]