[{"date":"06-03-2020","death":5637},{"date":"05-07-2020","death":3294},{"date":"05-18-2020","death":4419},{"date":"05-23-2020","death":4857},{"date":"05-14-2020","death":4034},{"date":"06-02-2020","death":5576},{"date":"06-08-2020","death":5915},{"date":"05-27-2020","death":5169},{"date":"04-25-2020","death":1941},{"date":"05-09-2020","death":3512},{"date":"06-04-2020","death":5696},{"date":"05-13-2020","death":3933},{"date":"06-10-2020","death":6014},{"date":"06-06-2020","death":5809},{"date":"05-08-2020","death":3404},{"date":"04-28-2020","death":2276},{"date":"05-05-2020","death":3071},{"date":"04-30-2020","death":2504},{"date":"05-15-2020","death":4133},{"date":"05-24-2020","death":4938},{"date":"05-28-2020","death":5242},{"date":"05-21-2020","death":4688},{"date":"05-31-2020","death":5449},{"date":"04-23-2020","death":1723},{"date":"05-12-2020","death":3830},{"date":"04-29-2020","death":2390},{"date":"05-11-2020","death":3726},{"date":"05-06-2020","death":3183},{"date":"05-30-2020","death":5382},{"date":"06-01-2020","death":5513},{"date":"06-11-2020","death":6061},{"date":"04-26-2020","death":2052},{"date":"05-02-2020","death":2731},{"date":"06-09-2020","death":5965},{"date":"05-20-2020","death":4600},{"date":"05-19-2020","death":4511},{"date":"05-10-2020","death":3620},{"date":"05-29-2020","death":5313},{"date":"06-14-2020","death":6192},{"date":"06-12-2020","death":6106},{"date":"06-05-2020","death":5754},{"date":"05-17-2020","death":4326},{"date":"06-15-2020","death":6233},{"date":"05-25-2020","death":5017},{"date":"04-27-2020","death":2164},{"date":"05-03-2020","death":2845},{"date":"05-04-2020","death":2958},{"date":"05-22-2020","death":4773},{"date":"05-26-2020","death":5094},{"date":"06-13-2020","death":6150},{"date":"06-07-2020","death":5863},{"date":"05-16-2020","death":4230},{"date":"04-24-2020","death":1831},{"date":"05-01-2020","death":2617}]