[{"date":"03-14-2020","death":"0","cases":"1"},{"date":"03-15-2020","death":"0","cases":"3"},{"date":"03-16-2020","death":"0","cases":"4"},{"date":"03-17-2020","death":"0","cases":"7"},{"date":"03-18-2020","death":"0","cases":"11"},{"date":"03-19-2020","death":"0","cases":"18"},{"date":"03-20-2020","death":"0","cases":"29"},{"date":"03-21-2020","death":"0","cases":"35"},{"date":"03-22-2020","death":"1","cases":"54"},{"date":"03-23-2020","death":"2","cases":"61"},{"date":"03-24-2020","death":"2","cases":"88"},{"date":"03-25-2020","death":"2","cases":"116"},{"date":"03-26-2020","death":"2","cases":"138"},{"date":"03-27-2020","death":"2","cases":"189"},{"date":"03-28-2020","death":"2","cases":"228"},{"date":"03-29-2020","death":"2","cases":"276"},{"date":"03-30-2020","death":"3","cases":"330"},{"date":"03-31-2020","death":"7","cases":"393"},{"date":"04-01-2020","death":"11","cases":"469"},{"date":"04-02-2020","death":"13","cases":"539"},{"date":"04-03-2020","death":"18","cases":"679"},{"date":"04-04-2020","death":"26","cases":"726"},{"date":"04-05-2020","death":"29","cases":"751"},{"date":"04-06-2020","death":"31","cases":"882"},{"date":"04-07-2020","death":"48","cases":"1045"},{"date":"04-08-2020","death":"68","cases":"1290"},{"date":"04-09-2020","death":"75","cases":"1471"},{"date":"04-10-2020","death":"88","cases":"1615"},{"date":"04-11-2020","death":"101","cases":"1832"},{"date":"04-12-2020","death":"116","cases":"1914"},{"date":"04-13-2020","death":"133","cases":"2243"},{"date":"04-14-2020","death":"153","cases":"2370"},{"date":"04-15-2020","death":"213","cases":"2570"},{"date":"04-16-2020","death":"243","cases":"2859"},{"date":"04-17-2020","death":"266","cases":"3015"},{"date":"04-18-2020","death":"289","cases":"3196"},{"date":"04-19-2020","death":"295","cases":"3351"},{"date":"04-20-2020","death":"369","cases":"3823"},{"date":"04-21-2020","death":"402","cases":"3951"},{"date":"04-22-2020","death":"442","cases":"4128"},{"date":"04-23-2020","death":"469","cases":"4303"},{"date":"04-24-2020","death":"511","cases":"4570"},{"date":"04-25-2020","death":"553","cases":"4761"},{"date":"04-26-2020","death":"579","cases":"4989"},{"date":"04-27-2020","death":"612","cases":"5157"},{"date":"04-28-2020","death":"643","cases":"5224"},{"date":"04-29-2020","death":"670","cases":"5388"},{"date":"04-30-2020","death":"698","cases":"5601"},{"date":"05-01-2020","death":"715","cases":"5931"},{"date":"05-02-2020","death":"741","cases":"6112"},{"date":"05-03-2020","death":"741","cases":"6112"},{"date":"05-04-2020","death":"773","cases":"6173"},{"date":"05-05-2020","death":"804","cases":"6351"},{"date":"05-06-2020","death":"842","cases":"6530"},{"date":"05-07-2020","death":"867","cases":"6750"},{"date":"05-08-2020","death":"884","cases":"6904"},{"date":"05-09-2020","death":"901","cases":"7105"},{"date":"05-10-2020","death":"909","cases":"7263"},{"date":"05-11-2020","death":"921","cases":"7358"},{"date":"05-12-2020","death":"931","cases":"7528"},{"date":"05-13-2020","death":"963","cases":"7732"},{"date":"05-14-2020","death":"999","cases":"7935"},{"date":"05-15-2020","death":"1025","cases":"8126"},{"date":"05-16-2020","death":"1044","cases":"8299"},{"date":"05-17-2020","death":"1069","cases":"8723"},{"date":"05-18-2020","death":"1084","cases":"8957"},{"date":"05-19-2020","death":"1090","cases":"9050"},{"date":"05-20-2020","death":"1116","cases":"9234"},{"date":"05-21-2020","death":"1133","cases":"9299"},{"date":"05-22-2020","death":"1155","cases":"9463"},{"date":"05-23-2020","death":"1169","cases":"9545"},{"date":"05-24-2020","death":"1175","cases":"9686"},{"date":"05-25-2020","death":"1187","cases":"9841"},{"date":"05-26-2020","death":"1193","cases":"9917"},{"date":"05-27-2020","death":"1203","cases":"9962"},{"date":"05-28-2020","death":"1208","cases":"10078"},{"date":"05-29-2020","death":"1222","cases":"10146"},{"date":"05-30-2020","death":"1238","cases":"10207"},{"date":"05-31-2020","death":"1250","cases":"10296"},{"date":"06-01-2020","death":"1254","cases":"10445"},{"date":"06-02-2020","death":"1253","cases":"10536"},{"date":"06-03-2020","death":"1259","cases":"10593"},{"date":"06-04-2020","death":"1266","cases":"10636"},{"date":"06-05-2020","death":"1277","cases":"10677"},{"date":"06-06-2020","death":"1279","cases":"10747"},{"date":"06-07-2020","death":"1287","cases":"10809"},{"date":"06-08-2020","death":"1291","cases":"10844"},{"date":"06-09-2020","death":"1291","cases":"10859"},{"date":"06-10-2020","death":"1303","cases":"10924"},{"date":"06-11-2020","death":"1308","cases":"10967"},{"date":"06-12-2020","death":"1313","cases":"11103"},{"date":"06-13-2020","death":"1321","cases":"11189"},{"date":"06-14-2020","death":"1327","cases":"11218"},{"date":"06-15-2020","death":"1328","cases":"11231"},{"date":"06-16-2020","death":"1330","cases":"11261"},{"date":"06-17-2020","death":"1331","cases":"11284"},{"date":"06-18-2020","death":"1336","cases":"11322"},{"date":"06-19-2020","death":"1341","cases":"11358"},{"date":"06-20-2020","death":"1344","cases":"11392"},{"date":"06-21-2020","death":"1350","cases":"11405"},{"date":"06-22-2020","death":"1350","cases":"11414"},{"date":"06-23-2020","death":"1352","cases":"11443"},{"date":"06-24-2020","death":"1356","cases":"11450"},{"date":"06-25-2020","death":"1362","cases":"11483"},{"date":"06-26-2020","death":"1365","cases":"11511"},{"date":"06-27-2020","death":"1369","cases":"11558"},{"date":"06-28-2020","death":"1369","cases":"11587"}]