[{"date":"02-04-2020","death":0,"hospitalizations":0},{"date":"02-05-2020","death":0,"hospitalizations":0},{"date":"02-06-2020","death":0,"hospitalizations":0},{"date":"02-07-2020","death":0,"hospitalizations":0},{"date":"02-08-2020","death":0,"hospitalizations":0},{"date":"02-09-2020","death":0,"hospitalizations":0},{"date":"02-10-2020","death":0,"hospitalizations":0},{"date":"02-11-2020","death":0,"hospitalizations":0},{"date":"02-12-2020","death":0,"hospitalizations":0},{"date":"02-13-2020","death":0,"hospitalizations":0},{"date":"02-14-2020","death":0,"hospitalizations":0},{"date":"02-15-2020","death":0,"hospitalizations":0},{"date":"02-16-2020","death":0,"hospitalizations":0},{"date":"02-17-2020","death":0,"hospitalizations":0},{"date":"02-18-2020","death":0,"hospitalizations":0},{"date":"02-19-2020","death":0,"hospitalizations":0},{"date":"02-20-2020","death":0,"hospitalizations":0},{"date":"02-21-2020","death":0,"hospitalizations":0},{"date":"02-22-2020","death":0,"hospitalizations":0},{"date":"02-23-2020","death":0,"hospitalizations":0},{"date":"02-24-2020","death":0,"hospitalizations":0},{"date":"02-25-2020","death":0,"hospitalizations":0},{"date":"02-26-2020","death":0,"hospitalizations":0},{"date":"02-27-2020","death":0,"hospitalizations":0},{"date":"02-28-2020","death":0,"hospitalizations":0},{"date":"02-29-2020","death":0,"hospitalizations":0},{"date":"03-01-2020","death":0,"hospitalizations":0},{"date":"03-02-2020","death":0,"hospitalizations":0},{"date":"03-03-2020","death":0,"hospitalizations":0},{"date":"03-04-2020","death":0,"hospitalizations":0},{"date":"03-05-2020","death":0,"hospitalizations":0},{"date":"03-06-2020","death":0,"hospitalizations":0},{"date":"03-07-2020","death":0,"hospitalizations":0},{"date":"03-08-2020","death":0,"hospitalizations":0},{"date":"03-09-2020","death":0,"hospitalizations":0},{"date":"03-10-2020","death":0,"hospitalizations":0},{"date":"03-11-2020","death":0,"hospitalizations":0},{"date":"03-12-2020","death":0,"hospitalizations":0},{"date":"03-13-2020","death":0,"hospitalizations":0},{"date":"03-14-2020","death":0,"hospitalizations":0},{"date":"03-15-2020","death":0,"hospitalizations":0},{"date":"03-16-2020","death":0,"hospitalizations":4.242},{"date":"03-17-2020","death":0,"hospitalizations":8.444},{"date":"03-18-2020","death":0,"hospitalizations":16.975},{"date":"03-19-2020","death":1,"hospitalizations":25.418},{"date":"03-20-2020","death":1,"hospitalizations":37.9705},{"date":"03-21-2020","death":2,"hospitalizations":54.398},{"date":"03-22-2020","death":4,"hospitalizations":78.084},{"date":"03-23-2020","death":6,"hospitalizations":103.3695},{"date":"03-24-2020","death":8,"hospitalizations":136.223},{"date":"03-25-2020","death":15,"hospitalizations":178.3255},{"date":"03-26-2020","death":18,"hospitalizations":227.252},{"date":"03-27-2020","death":22,"hospitalizations":289.4765},{"date":"03-28-2020","death":34,"hospitalizations":359.4205},{"date":"03-29-2020","death":41,"hospitalizations":439.0345},{"date":"03-30-2020","death":50,"hospitalizations":529.8165},{"date":"03-31-2020","death":63,"hospitalizations":628.7435},{"date":"04-01-2020","death":74,"hospitalizations":733.9075},{"date":"04-02-2020","death":90,"hospitalizations":850.848},{"date":"04-03-2020","death":102,"hospitalizations":969.3745},{"date":"04-04-2020","death":136,"hospitalizations":1096.5975},{"date":"04-05-2020","death":151,"hospitalizations":1227.706},{"date":"04-06-2020","death":179,"hospitalizations":1364.8865},{"date":"04-07-2020","death":247,"hospitalizations":1505.7135},{"date":"04-08-2020","death":318,"hospitalizations":1647.094},{"date":"04-09-2020","death":345,"hospitalizations":1789.1765},{"date":"04-10-2020","death":418,"hospitalizations":1936.7435},{"date":"04-11-2020","death":503,"hospitalizations":2080.4955},{"date":"04-12-2020","death":557,"hospitalizations":2226.409},{"date":"04-13-2020","death":589,"hospitalizations":2367.665},{"date":"04-14-2020","death":691,"hospitalizations":2505.979},{"date":"04-15-2020","death":779,"hospitalizations":2645.0785},{"date":"04-16-2020","death":841,"hospitalizations":2782.6355},{"date":"04-17-2020","death":921,"hospitalizations":2911.038},{"date":"04-18-2020","death":1042,"hospitalizations":3033.94},{"date":"04-19-2020","death":1276,"hospitalizations":3149.362},{"date":"04-20-2020","death":1348,"hospitalizations":3255.4075},{"date":"04-21-2020","death":1614,"hospitalizations":3362.586},{"date":"04-22-2020","death":1673,"hospitalizations":3452.87},{"date":"04-23-2020","death":1724,"hospitalizations":3536.3565},{"date":"04-24-2020","death":1747,"hospitalizations":3610.941},{"date":"04-25-2020","death":1793,"hospitalizations":3676.797},{"date":"04-26-2020","death":1816,"hospitalizations":3732.5915},{"date":"04-27-2020","death":1886,"hospitalizations":3780.6825},{"date":"04-28-2020","death":2046,"hospitalizations":3812.068},{"date":"04-29-2020","death":2373,"hospitalizations":3834.8485},{"date":"04-30-2020","death":2475,"hospitalizations":3844.1},{"date":"05-01-2020","death":2635,"hospitalizations":3845.1435},{"date":"05-02-2020","death":2695,"hospitalizations":3838.972},{"date":"05-03-2020","death":2720,"hospitalizations":3820.518},{"date":"05-04-2020","death":2838,"hospitalizations":3792.3165},{"date":"05-05-2020","death":3179,"hospitalizations":3756.175},{"date":"05-06-2020","death":3345,"hospitalizations":3716.4895},{"date":"05-07-2020","death":3589,"hospitalizations":3671.5885},{"date":"05-08-2020","death":3715,"hospitalizations":3616.886},{"date":"05-09-2020","death":3779,"hospitalizations":3558.667},{"date":"05-10-2020","death":3806,"hospitalizations":3496.8825},{"date":"05-11-2020","death":3832,"hospitalizations":3427.9595},{"date":"05-12-2020","death":3914,"hospitalizations":3355.7435},{"date":"05-13-2020","death":4094,"hospitalizations":3276.2945},{"date":"05-14-2020","death":4288,"hospitalizations":3199.372},{"date":"05-15-2020","death":4422,"hospitalizations":3120.7065},{"date":"05-16-2020","death":4480,"hospitalizations":3033.959},{"date":"05-17-2020","death":4495,"hospitalizations":2946.59},{"date":"05-18-2020","death":4515,"hospitalizations":2860.252},{"date":"05-19-2020","death":4628,"hospitalizations":2774.0725},{"date":"05-20-2020","death":4770,"hospitalizations":2689.987},{"date":"05-21-2020","death":4869,"hospitalizations":2598.809},{"date":"05-22-2020","death":5010,"hospitalizations":2508.1445},{"date":"05-23-2020","death":5112,"hospitalizations":2423.12},{"date":"05-24-2020","death":5136,"hospitalizations":2338.8725},{"date":"05-25-2020","death":5146,"hospitalizations":2257.3365},{"date":"05-26-2020","death":5163,"hospitalizations":2174.5985},{"date":"05-27-2020","death":5265,"hospitalizations":2091.193},{"date":"05-28-2020","death":5373,"hospitalizations":2014.571},{"date":"05-29-2020","death":5464,"hospitalizations":1939.4665},{"date":"05-30-2020","death":5537,"hospitalizations":1866.083},{"date":"05-31-2020","death":5555,"hospitalizations":1791.66},{"date":"06-01-2020","death":5567,"hospitalizations":1723.3355},{"date":"06-02-2020","death":5667,"hospitalizations":1656.1275},{"date":"06-03-2020","death":5742,"hospitalizations":1590.336},{"date":"06-04-2020","death":5832,"hospitalizations":1525.524},{"date":"06-05-2020","death":5898,"hospitalizations":1465.178},{"date":"06-06-2020","death":5931,"hospitalizations":1405.69},{"date":"06-07-2020","death":5943,"hospitalizations":1352.328},{"date":"06-08-2020","death":5953,"hospitalizations":1295.048},{"date":"06-09-2020","death":6014,"hospitalizations":1242.514},{"date":"06-10-2020","death":6062,"hospitalizations":1196.086},{"date":"06-11-2020","death":6113,"hospitalizations":1151.358},{"date":"06-12-2020","death":6162,"hospitalizations":1113.0695},{"date":"06-13-2020","death":6211,"hospitalizations":1078.3205},{"date":"06-14-2020","death":6215,"hospitalizations":1047.6345},{"date":"06-15-2020","death":6243,"hospitalizations":1021.8795},{"date":"06-16-2020","death":6276,"hospitalizations":1000.888},{"date":"06-17-2020","death":6319,"hospitalizations":983.532},{"date":"06-18-2020","death":6361,"hospitalizations":969.047},{"date":"06-19-2020","death":6399,"hospitalizations":955.952},{"date":"06-20-2020","death":6419,"hospitalizations":950.849},{"date":"06-21-2020","death":6423,"hospitalizations":947.702},{"date":"06-22-2020","death":6426,"hospitalizations":947.1595},{"date":"06-23-2020","death":6464,"hospitalizations":945.624},{"date":"06-24-2020","death":6518,"hospitalizations":946.146},{"date":"06-25-2020","death":6557,"hospitalizations":947.4115},{"date":"06-26-2020","death":6579,"hospitalizations":948.243},{"date":"06-27-2020","death":6603,"hospitalizations":947.181},{"date":"06-28-2020","death":6419.70203844929,"hospitalizations":946.295},{"date":"06-29-2020","death":6449.68424790219,"hospitalizations":945.901},{"date":"06-30-2020","death":6479.71223680231,"hospitalizations":946.4565},{"date":"07-01-2020","death":6509.75534909219,"hospitalizations":945.2085},{"date":"07-02-2020","death":6539.77894755895,"hospitalizations":944.2635},{"date":"07-03-2020","death":6569.75573013663,"hospitalizations":941.897},{"date":"07-04-2020","death":6599.6696370227,"hospitalizations":938.696},{"date":"07-05-2020","death":6629.5029651416,"hospitalizations":935.434},{"date":"07-06-2020","death":6659.21925630305,"hospitalizations":931.951},{"date":"07-07-2020","death":6688.81691038225,"hospitalizations":927.9055},{"date":"07-08-2020","death":6718.28762935008,"hospitalizations":923.9335},{"date":"07-09-2020","death":6747.61372445333,"hospitalizations":916.846},{"date":"07-10-2020","death":6776.77502045101,"hospitalizations":910.855},{"date":"07-11-2020","death":6805.75047931197,"hospitalizations":903.557},{"date":"07-12-2020","death":6834.512029339,"hospitalizations":895.662},{"date":"07-13-2020","death":6863.02492884371,"hospitalizations":887.1995},{"date":"07-14-2020","death":6891.25329779903,"hospitalizations":877.351},{"date":"07-15-2020","death":6919.16603579983,"hospitalizations":866.6295},{"date":"07-16-2020","death":6946.73589416912,"hospitalizations":857.2535},{"date":"07-17-2020","death":6973.94427332781,"hospitalizations":846.709},{"date":"07-18-2020","death":7000.78380433536,"hospitalizations":834.745},{"date":"07-19-2020","death":7027.24447286231,"hospitalizations":822.8135},{"date":"07-20-2020","death":7053.31580718873,"hospitalizations":810.3615},{"date":"07-21-2020","death":7078.99209827884,"hospitalizations":797.933},{"date":"07-22-2020","death":7104.26592926793,"hospitalizations":786.1245},{"date":"07-23-2020","death":7129.12661379181,"hospitalizations":773.307},{"date":"07-24-2020","death":7153.57209826211,"hospitalizations":760.292},{"date":"07-25-2020","death":7177.60666161603,"hospitalizations":747.29},{"date":"07-26-2020","death":7201.22979259213,"hospitalizations":734.431},{"date":"07-27-2020","death":7224.43846588604,"hospitalizations":721.2395},{"date":"07-28-2020","death":7247.23034139155,"hospitalizations":708.3245},{"date":"07-29-2020","death":7269.6010470738,"hospitalizations":694.4155},{"date":"07-30-2020","death":7291.54317847216,"hospitalizations":680.484},{"date":"07-31-2020","death":7313.05510458892,"hospitalizations":667.593},{"date":"08-01-2020","death":7334.14213070437,"hospitalizations":654.5155},{"date":"08-02-2020","death":7354.80860159506,"hospitalizations":641.0535},{"date":"08-03-2020","death":7375.05676880261,"hospitalizations":627.6145},{"date":"08-04-2020","death":7394.88912675631,"hospitalizations":613.793},{"date":"08-05-2020","death":7414.30648106109,"hospitalizations":600.657},{"date":"08-06-2020","death":7433.30718336816,"hospitalizations":588.395},{"date":"08-07-2020","death":7451.89349706403,"hospitalizations":575.205},{"date":"08-08-2020","death":7470.07264516571,"hospitalizations":563.078},{"date":"08-09-2020","death":7487.85301316788,"hospitalizations":551.6935},{"date":"08-10-2020","death":7505.243995161,"hospitalizations":540.176},{"date":"08-11-2020","death":7522.25604424861,"hospitalizations":529.7155},{"date":"08-12-2020","death":7538.89843441715,"hospitalizations":518.145},{"date":"08-13-2020","death":7555.17850374012,"hospitalizations":506.961},{"date":"08-14-2020","death":7571.10659593581,"hospitalizations":496.0245},{"date":"08-15-2020","death":7586.6971522752,"hospitalizations":485.661},{"date":"08-16-2020","death":7601.96458967095,"hospitalizations":474.864},{"date":"08-17-2020","death":7616.9199215632,"hospitalizations":465.5325},{"date":"08-18-2020","death":7631.57180408494,"hospitalizations":455.564},{"date":"08-19-2020","death":7645.92803683557,"hospitalizations":447.0325},{"date":"08-20-2020","death":7659.99488879901,"hospitalizations":438.6085},{"date":"08-21-2020","death":7673.77958545153,"hospitalizations":429.571},{"date":"08-22-2020","death":7687.29112173635,"hospitalizations":420.667},{"date":"08-23-2020","death":7700.53857045575,"hospitalizations":412.6635},{"date":"08-24-2020","death":7713.53054173077,"hospitalizations":404.1085},{"date":"08-25-2020","death":7726.27540741654,"hospitalizations":396.44},{"date":"08-26-2020","death":7738.78076185594,"hospitalizations":389.702},{"date":"08-27-2020","death":7751.05299324456,"hospitalizations":382.7965},{"date":"08-28-2020","death":7763.09848385576,"hospitalizations":378.053},{"date":"08-29-2020","death":7774.92437337066,"hospitalizations":374.0955},{"date":"08-30-2020","death":7786.53816343756,"hospitalizations":370.266},{"date":"08-31-2020","death":7797.99972763313,"hospitalizations":367.363},{"date":"09-01-2020","death":7809.38281359117,"hospitalizations":364.851},{"date":"09-02-2020","death":7820.7209011612,"hospitalizations":362.016},{"date":"09-03-2020","death":7832.03382354877,"hospitalizations":359.554},{"date":"09-04-2020","death":7843.34544816144,"hospitalizations":357.3985},{"date":"09-05-2020","death":7854.61314203416,"hospitalizations":355.0985},{"date":"09-06-2020","death":7865.78410185854,"hospitalizations":352.6375},{"date":"09-07-2020","death":7876.87249961508,"hospitalizations":350.807},{"date":"09-08-2020","death":7887.88870086037,"hospitalizations":348.429},{"date":"09-09-2020","death":7898.84085291659,"hospitalizations":346.8965},{"date":"09-10-2020","death":7909.73558897223,"hospitalizations":345.303},{"date":"09-11-2020","death":7920.57759102219,"hospitalizations":343.4805},{"date":"09-12-2020","death":7931.37045367506,"hospitalizations":342.3495},{"date":"09-13-2020","death":7942.11848487027,"hospitalizations":340.7605},{"date":"09-14-2020","death":7952.82681931171,"hospitalizations":338.89},{"date":"09-15-2020","death":7963.50072607751,"hospitalizations":338.108},{"date":"09-16-2020","death":7974.1458731108,"hospitalizations":337.057},{"date":"09-17-2020","death":7984.7681302023,"hospitalizations":336.5385},{"date":"09-18-2020","death":7995.37156190709,"hospitalizations":336.4895},{"date":"09-19-2020","death":8005.95878025107,"hospitalizations":336.0345},{"date":"09-20-2020","death":8016.53340916474,"hospitalizations":336.121},{"date":"09-21-2020","death":8027.10032046965,"hospitalizations":336.3105},{"date":"09-22-2020","death":8037.66468396042,"hospitalizations":335.805},{"date":"09-23-2020","death":8048.2324294017,"hospitalizations":336.281},{"date":"09-24-2020","death":8058.81014006302,"hospitalizations":336.998},{"date":"09-25-2020","death":8069.40212351382,"hospitalizations":337.347},{"date":"09-26-2020","death":8080.01057357151,"hospitalizations":338.0465},{"date":"09-27-2020","death":8090.63882054274,"hospitalizations":339.2565},{"date":"09-28-2020","death":8101.2917827099,"hospitalizations":340.398},{"date":"09-29-2020","death":8111.97481827811,"hospitalizations":341.5845},{"date":"09-30-2020","death":8122.69438959388,"hospitalizations":342.518},{"date":"10-01-2020","death":8133.45805154395,"hospitalizations":343.7625}]